{"cameraMode":{"drawMode":0,"name":"Shaded","section":"Shading Mode"},"sceneLighting":false,"audioPlay":false,"sceneViewState":{"showFog":true,"showMaterialUpdate":false,"showSkybox":false,"showFlares":true,"showImageEffects":true,"showParticleSystems":true},"in2DMode":false,"pivot":{"x":1.4969605207443238,"y":3.0864429473876955,"z":717.86083984375},"rotation":{"x":0.06608051061630249,"y":-0.6949547529220581,"z":0.0643937885761261,"w":0.7131156325340271},"size":0.5791336894035339,"orthographic":false}